napari_splineit/__init__.py
napari_splineit/_reader.py
napari_splineit/_sample_data.py
napari_splineit/_version.py
napari_splineit/_widget.py
napari_splineit/_writer.py
napari_splineit/napari.yml
napari_splineit/_tests/__init__.py
napari_splineit/_tests/test_sample_data.py
napari_splineit/_tests/test_widget.py
napari_splineit/interpolation/__init__.py
napari_splineit/interpolation/cubic.py
napari_splineit/interpolation/interpolator_base.py
napari_splineit/interpolation/spline.py
napari_splineit/interpolation/splinegenerator.py
napari_splineit/interpolation/uhlmann.py
napari_splineit/interpolation/utils.py
napari_splineit/layer/__init__.py
napari_splineit/layer/_ctrl_layer.py
napari_splineit/layer/_interpolated_layer.py
napari_splineit/layer/_shape_list.py
napari_splineit/layer/layer_factory.py
napari_splineit/widgets/__init__.py
napari_splineit/widgets/double_spin_slider.py
napari_splineit/widgets/spin_slider.py
napari_splineit-0.3.0.dist-info/LICENSE
napari_splineit-0.3.0.dist-info/METADATA
napari_splineit-0.3.0.dist-info/WHEEL
napari_splineit-0.3.0.dist-info/entry_points.txt
napari_splineit-0.3.0.dist-info/top_level.txt
napari_splineit-0.3.0.dist-info/RECORD
