Metadata-Version: 2.1
Name: napari-splineit
Version: 0.3.0
Summary: A napari plugin for spline manipulation
Home-page: https://github.com/uhlmanngroup/napari-splineit
Author: Thorsten Beier
Author-email: derthorstenbeier@gmail.com
License: BSD-3-Clause
Project-URL: Bug Tracker, https://github.com/uhlmanngroup/napari-splineit/issues
Project-URL: Documentation, https://github.com/uhlmanngroup/napari-splineit#README.md
Project-URL: Source Code, https://github.com/uhlmanngroup/napari-splineit
Project-URL: User Support, https://github.com/uhlmanngroup/napari-splineit/issues
Classifier: Development Status :: 2 - Pre-Alpha
Classifier: Framework :: napari
Classifier: Intended Audience :: Developers
Classifier: License :: OSI Approved :: BSD License
Classifier: Operating System :: OS Independent
Classifier: Programming Language :: Python
Classifier: Programming Language :: Python :: 3
Classifier: Programming Language :: Python :: 3 :: Only
Classifier: Programming Language :: Python :: 3.7
Classifier: Programming Language :: Python :: 3.8
Classifier: Programming Language :: Python :: 3.9
Classifier: Programming Language :: Python :: 3.10
Classifier: Topic :: Software Development :: Testing
Requires-Python: >=3.7
License-File: LICENSE
Requires-Dist: numpy
Requires-Dist: qtpy
Requires-Dist: scikit-image
Requires-Dist: scipy
Provides-Extra: testing
Requires-Dist: napari ; extra == 'testing'
Requires-Dist: pyqt5 ; extra == 'testing'
Requires-Dist: pytest ; extra == 'testing'
Requires-Dist: pytest-cov ; extra == 'testing'
Requires-Dist: pytest-qt ; extra == 'testing'
Requires-Dist: tox ; extra == 'testing'
